better_twitter/__init__.py
better_twitter/main.py
better_twitter-0.1.0.dist-info/AUTHORS.rst
better_twitter-0.1.0.dist-info/METADATA
better_twitter-0.1.0.dist-info/WHEEL
better_twitter-0.1.0.dist-info/entry_points.txt
better_twitter-0.1.0.dist-info/top_level.txt
better_twitter-0.1.0.dist-info/RECORD
