Metadata-Version: 2.1
Name: better-twitter
Version: 0.1.0
Summary: A python package to block and mute fake and toxic twitter accounts in an automated and easy way.
Home-page: https://github.com/saeedesmaili/better-twitter
Author: Saeed Esmaili
Author-email: me@saeedesmaili.com
License: MIT license
Keywords: twitter
Platform: UNKNOWN
Classifier: Intended Audience :: Developers
Classifier: License :: OSI Approved :: MIT License
Classifier: Programming Language :: Python
Classifier: Programming Language :: Python :: 3
Classifier: Programming Language :: Python :: 3.6
Classifier: Programming Language :: Python :: 3.7
Classifier: Programming Language :: Python :: 3.8
Classifier: Programming Language :: Python :: 3.9
Classifier: Operating System :: OS Independent
License-File: AUTHORS.rst
Requires-Dist: pandas
Requires-Dist: python-twitter
Requires-Dist: pendulum
